golden_retrievers/__init__.py
golden_retrievers-0.1.0.dist-info/METADATA
golden_retrievers-0.1.0.dist-info/WHEEL
golden_retrievers-0.1.0.dist-info/RECORD
