Metadata-Version: 2.4
Name: golden-retrievers
Version: 0.1.0
Summary: Stories about the wonderful goldens
Requires-Python: >=3.12
Requires-Dist: svlearn-bootcamp>=0.1.7
